{
  "date": "2026-06-19",
  "generated_at": "2026-06-20T18:37:12+09:00",
  "items": [
    {
      "category": "job",
      "title": "[에이블리코퍼레이션] 백엔드 개발 인턴",
      "org": "에이블리코퍼레이션",
      "url": "https://www.wanted.co.kr/wd/87730",
      "posted_date": "2026-06-19",
      "deadline": null,
      "tags": ["백엔드", "인턴", "Java", "Python"],
      "summary": "패션 플랫폼 에이블리 이벤트 백엔드 API 및 백오피스 서비스 개발. Java·Python·Go 중 하나 이상 능숙, RDBMS 경험 필요."
    },
    {
      "category": "job",
      "title": "[디웨일] [인턴] 백엔드(JAVA) 개발자",
      "org": "디웨일",
      "url": "https://www.wanted.co.kr/wd/271591",
      "posted_date": "2026-06-19",
      "deadline": null,
      "tags": ["백엔드", "인턴", "Java", "Spring", "AWS"],
      "summary": "Spring 기반 웹 서버 개발 및 AWS 인프라 운영 인턴. RDB 경험 필수, 상시 채용."
    },
    {
      "category": "job",
      "title": "[티맥스메타에이아이] 백엔드 개발자 (신입/주니어)",
      "org": "티맥스메타에이아이",
      "url": "https://www.wanted.co.kr/wd/211482",
      "posted_date": "2026-06-19",
      "deadline": null,
      "tags": ["백엔드", "신입", "Java", "Spring Boot", "Redis"],
      "summary": "Java/Spring Boot 및 MariaDB·Redis 환경의 신입 백엔드 개발자 모집. 4년제 졸업자 대상, REST API 설계 역량 필요."
    },
    {
      "category": "job",
      "title": "[온다(ONDA)] R&D 백엔드 개발자 (신입)",
      "org": "온다(ONDA)",
      "url": "https://www.wanted.co.kr/wd/18646",
      "posted_date": "2026-06-19",
      "deadline": null,
      "tags": ["백엔드", "신입", "Node.js", "TypeScript", "R&D"],
      "summary": "여행·예약 플랫폼 ONDA의 R&D 백엔드 신입. RESTful API 및 RDBMS/NoSQL 경험 필수, TypeScript/Node.js 우대."
    },
    {
      "category": "job",
      "title": "[그래픽] [인턴] 백엔드 개발자(Kotlin, Spring)",
      "org": "주식회사 그래픽",
      "url": "https://www.wanted.co.kr/wd/297193",
      "posted_date": "2026-06-19",
      "deadline": null,
      "tags": ["백엔드", "인턴", "Kotlin", "Spring", "클라우드"],
      "summary": "Kotlin·Spring 기반 REST API 개발 및 클라우드 인프라 관리 인턴. 컴퓨터공학 전공 지식, AI 활용 능력 우대."
    },
    {
      "category": "competition",
      "title": "2026 호남IS해커톤",
      "org": "광주정보문화산업진흥원·제주산학융합원 (과기부 주최)",
      "url": "https://honam-is-hackathon.com/",
      "posted_date": "2026-06-19",
      "deadline": "2026-06-30",
      "tags": ["해커톤", "AI", "대학생", "지역", "데이터"],
      "summary": "호남권(광주·전남·전북·제주) AI 데이터 활용 해커톤. 만 19세 이상 4~6인 팀, 팀원 중 지역 관련자 1인 필수, 총 500만원 상금."
    }
  ]
}
